data_retrieval/__init__.py
data_retrieval/errors.py
data_retrieval/settings.py
data_retrieval/agents/__init__.py
data_retrieval/agents/base.py
data_retrieval/agents/tool_use_agent.py
data_retrieval/agents/react_agent/__init__.py
data_retrieval/agents/react_agent/base.py
data_retrieval/agents/react_agent/react_agent.py
data_retrieval/agents/react_agent/react_agent_dl.py
data_retrieval/api/__init__.py
data_retrieval/api/ad_api.py
data_retrieval/api/af_api.py
data_retrieval/api/agent_retrieval.py
data_retrieval/api/auth.py
data_retrieval/api/base.py
data_retrieval/api/data_model.py
data_retrieval/api/error.py
data_retrieval/api/vega.py
data_retrieval/callbacks/__init__.py
data_retrieval/callbacks/agent_callbacks.py
data_retrieval/datasource/__init__.py
data_retrieval/datasource/af_indicator.py
data_retrieval/datasource/api_base.py
data_retrieval/datasource/base.py
data_retrieval/datasource/db_base.py
data_retrieval/datasource/dimension_reduce.py
data_retrieval/datasource/dip_dataview.py
data_retrieval/datasource/dip_metric.py
data_retrieval/datasource/sqlite_ds.py
data_retrieval/datasource/vega_connector.py
data_retrieval/datasource/vega_datasource.py
data_retrieval/logs/__init__.py
data_retrieval/logs/logger.py
data_retrieval/parsers/__init__.py
data_retrieval/parsers/agent_parser.py
data_retrieval/parsers/base.py
data_retrieval/parsers/text2metric_parser.py
data_retrieval/parsers/text2sql_parser.py
data_retrieval/prompts/__init__.py
data_retrieval/prompts/base.py
data_retrieval/prompts/agent_prompts/__init__.py
data_retrieval/prompts/agent_prompts/tool_use_prompt.py
data_retrieval/prompts/agent_prompts/react_agent_prompt/__init__.py
data_retrieval/prompts/agent_prompts/react_agent_prompt/deepseek_r1.py
data_retrieval/prompts/agent_prompts/react_agent_prompt/default.py
data_retrieval/prompts/agent_prompts/react_agent_prompt/langchain.py
data_retrieval/prompts/manager/__init__.py
data_retrieval/prompts/manager/ad.py
data_retrieval/prompts/manager/base.py
kweaver_data_retrieval-0.1.2.dist-info/METADATA
kweaver_data_retrieval-0.1.2.dist-info/WHEEL
kweaver_data_retrieval-0.1.2.dist-info/top_level.txt
kweaver_data_retrieval-0.1.2.dist-info/RECORD
